ckstats/__init__.py
ckstats/chart.py
ckstats/constants.py
ckstats/generator.py
ckstats/renderers/__init__.py
ckstats/renderers/renderers.py
ckstats/renderers/pdf/__init__.py
ckstats/renderers/pdf/bar_series.py
ckstats/renderers/pdf/line_series.py
ckstats/renderers/pdf/title.py
ckstats/renderers/pdf/x_axis.py
ckstats/renderers/pdf/y_axis.py
ckstats/renderers/png/__init__.py
ckstats/renderers/png/bar_series.py
ckstats/renderers/png/line_series.py
ckstats/renderers/png/title.py
ckstats/renderers/png/x_axis.py
ckstats/renderers/png/y_axis.py
ckstats-1.0.1.dist-info/LICENSE
ckstats-1.0.1.dist-info/METADATA
ckstats-1.0.1.dist-info/WHEEL
ckstats-1.0.1.dist-info/top_level.txt
ckstats-1.0.1.dist-info/RECORD
