Metadata-Version: 2.1
Name: ckstats
Version: 1.0.1
Summary: A simple Python package for generating charts.
Home-page: https://github.com/chiraag-kakar/ckstats
Author: Chiraag Kakar
Author-email: ck2222@cse.jgec.ac.in
License: MIT
Platform: UNKNOWN
Classifier: License :: OSI Approved :: MIT License
Classifier: Programming Language :: Python :: 3
Classifier: Programming Language :: Python :: 3.7
Requires-Dist: Pillow
Requires-Dist: reportlab
